taskfile_help/__init__.py
taskfile_help/__main__.py
taskfile_help/completion.py
taskfile_help/config.py
taskfile_help/discovery.py
taskfile_help/output.py
taskfile_help/parser.py
taskfile_help/search.py
taskfile_help/taskfile_help.py
taskfile_help/two_step_parser.py
taskfile_help/validator.py
taskfile_help-0.4.2.dist-info/METADATA
taskfile_help-0.4.2.dist-info/WHEEL
taskfile_help-0.4.2.dist-info/entry_points.txt
taskfile_help-0.4.2.dist-info/licenses/LICENSE
taskfile_help-0.4.2.dist-info/RECORD
