Metadata-Version: 2.4
Name: taskfile-help
Version: 0.4.2
Summary: Dynamic Taskfile help generator with automatic grouping and namespace support
Project-URL: Homepage, https://github.com/royw/taskfile_help
Project-URL: Repository, https://github.com/royw/taskfile_help
Project-URL: Issues, https://github.com/royw/taskfile_help/issues
Author-email: Roy Wright <roy@wright.org>
License-Expression: MIT
License-File: LICENSE
Keywords: cli,help,task,taskfile,yaml
Classifier: Development Status :: 4 - Beta
Classifier: Intended Audience :: Developers
Classifier: License :: OSI Approved :: MIT License
Classifier: Programming Language :: Python :: 3
Classifier: Programming Language :: Python :: 3.11
Classifier: Programming Language :: Python :: 3.12
Classifier: Programming Language :: Python :: 3.13
Classifier: Topic :: Software Development :: Build Tools
Classifier: Topic :: Utilities
Requires-Python: >=3.11
Requires-Dist: python-dotenv>=1.0.0
Requires-Dist: pyyaml>=6.0.3
